<?xml version="1.0" encoding="utf-8" standalone="no"?><API><API_Name>Amazon SWF</API_Name><API_Homepage>http://aws.amazon.com/swf/</API_Homepage><API_Endpoint>https://swf.us-east-1.amazonaws.com</API_Endpoint><API_Provider>http://amazon.com</API_Provider><APIhub_URL/><Protocol___Formats>JSON </Protocol___Formats><API_Forum>https://forums.aws.amazon.com/forum.jspa?forumID=133</API_Forum><Other_options>JSON-RPC</Other_options><Secondary_Categories>Cloud</Secondary_Categories><Primary_Category>Enterprise</Primary_Category></API>