<?xml version="1.0" encoding="utf-8" standalone="no"?><API><API_Name>Apigee OAuth</API_Name><Contact_Email>oauthapi@apigee.com</Contact_Email><API_Homepage>http://developer.apigee.com/</API_Homepage><API_Kits>JavaScript, Java, Objective C</API_Kits><API_Provider>http://apigee.com/</API_Provider><APIhub_URL/><Protocol___Formats>REST </Protocol___Formats><Console_URL>https://apigee.com/apigee/embed/console/apigee</Console_URL><Developer_Support>http://support.apigee.com/apigee</Developer_Support><Authentication_Mode>HTTP Basic Authentication</Authentication_Mode><Secondary_Categories>Authentication</Secondary_Categories><SSL_Support>Yes</SSL_Support><Primary_Category>Security</Primary_Category></API>