<?xml version="1.0" encoding="utf-8" standalone="no"?><API><API_Name>Bing Maps Search</API_Name><API_Homepage>http://msdn.microsoft.com/en-us/library/cc980849.aspx</API_Homepage><API_Provider>http://www.microsoft.com</API_Provider><APIhub_URL/><Protocol___Formats>SOAP </Protocol___Formats><API_Forum>http://social.msdn.microsoft.com/forums/en-US/vemapcontroldev/threads/</API_Forum><Authentication_Mode>API Key</Authentication_Mode><Secondary_Categories>Search</Secondary_Categories><SSL_Support>Yes</SSL_Support><Primary_Category>Mapping</Primary_Category></API>