<?xml version="1.0" encoding="utf-8" standalone="no"?><API><API_Name>Cigna Health</API_Name><Contact_Email>http://www.cigna.com/aboutus/contact-us</Contact_Email><API_Homepage>https://developer.cigna.com/home/pages/home#/</API_Homepage><API_Provider>http://www.cigna.com</API_Provider><APIhub_URL/><Protocol___Formats>REST </Protocol___Formats><Authentication_Mode>OAuth 2.0</Authentication_Mode><Secondary_Categories>Real Time</Secondary_Categories><Primary_Category>Medical</Primary_Category></API>