<?xml version="1.0" encoding="utf-8" standalone="no"?><API><API_Name>ClickBook</API_Name><Contact_Email>md@clickbook.net</Contact_Email><API_Homepage>http://clickbook.net/interface</API_Homepage><API_Endpoint>http://clickbook.net/interface</API_Endpoint><API_Provider>http://www.clickbook.net/</API_Provider><APIhub_URL/><Protocol___Formats>SOAP </Protocol___Formats><Developer_Support>http://www.clickbook.net/Contact</Developer_Support><Authentication_Mode>API Key &amp; IP Address</Authentication_Mode><Secondary_Categories>Scheduling</Secondary_Categories><SSL_Support>Yes</SSL_Support><Primary_Category>Calendars</Primary_Category></API>