<?xml version="1.0" encoding="utf-8" standalone="no"?><API><API_Name>CORDC HFRADAR Maps</API_Name><Contact_Email>webmaster@sio.ucsd.edu</Contact_Email><API_Homepage>http://cordc.ucsd.edu/projects/mapping/api/</API_Homepage><API_Endpoint>http://cordc.ucsd.edu/js/RTV/RTVTileLayer.js</API_Endpoint><API_Provider>http://sio.ucsd.edu/</API_Provider><APIhub_URL/><Authentication_Mode>Public</Authentication_Mode><Other_options>HTML, Javascript</Other_options><Secondary_Categories>Mapping</Secondary_Categories><SSL_Support>No</SSL_Support><Primary_Category>Weather</Primary_Category></API>