<?xml version="1.0" encoding="utf-8" standalone="no"?><API><API_Name>DDBC Authority Database</API_Name><Contact_Email>ddbc@ddbc.edu.tw</Contact_Email><API_Homepage>http://authority.ddbc.edu.tw/docs/services/</API_Homepage><API_Endpoint>http://authority.ddbc.edu.tw/webwidget/getAuthorityData.php</API_Endpoint><API_Provider>http://www.ddbc.edu.tw/</API_Provider><APIhub_URL/><Protocol___Formats>REST </Protocol___Formats><Authentication_Mode>Public</Authentication_Mode><Other_options>Javascript</Other_options><Secondary_Categories>Religion</Secondary_Categories><SSL_Support>No</SSL_Support><Primary_Category>Reference</Primary_Category></API>