<?xml version="1.0" encoding="utf-8" standalone="no"?><API><API_Name>Europass</API_Name><API_Homepage>http://europass.cedefop.europa.eu/TechnicalResources/Web_Services/europass-rest-...</API_Homepage><API_Provider>http://www.europa.eu</API_Provider><APIhub_URL/><Protocol___Formats>REST </Protocol___Formats><Authentication_Mode>HTTP Basic Authentication</Authentication_Mode><Secondary_Categories>European</Secondary_Categories><SSL_Support>Yes</SSL_Support><Primary_Category>Jobs</Primary_Category></API>