<?xml version="1.0" encoding="utf-8" standalone="no"?><API><API_Name>Eventbrite</API_Name><API_Homepage>http://developer.eventbrite.com/</API_Homepage><API_Kits>http://developer.eventbrite.com/docs/</API_Kits><API_Provider>http://www.eventbrite.com</API_Provider><Protocol___Formats>HTTP </Protocol___Formats><Console_URL>http://apigee.com/console/eventbrite</Console_URL><SSL_Support>Yes</SSL_Support><Contact_Email>api@eventbrite.com</Contact_Email><API_Endpoint>https://www.eventbriteapi.com/</API_Endpoint><Twitter_Url>http://twitter.com/EventbriteAPI</Twitter_Url><APIhub_URL/><Developer_Support>http://developer.eventbrite.com/contact-us/</Developer_Support><API_Forum>https://groups.google.com/forum/#!forum/eventbrite-api</API_Forum><Authentication_Mode>OAuth2.0</Authentication_Mode><Secondary_Categories>Tickets</Secondary_Categories><Primary_Category>Events</Primary_Category></API>