<?xml version="1.0" encoding="utf-8" standalone="no"?><API><API_Name>ExpertFlyer</API_Name><Contact_Email>bizdev@expertflyer.com</Contact_Email><API_Homepage>http://www.ExpertFlyer.com</API_Homepage><API_Provider>http://www.ExpertFlyer.com</API_Provider><APIhub_URL/><Protocol___Formats>REST </Protocol___Formats><Developer_Support>bizdev -at- expertflyer.com</Developer_Support><Authentication_Mode>HTTP</Authentication_Mode><Secondary_Categories>Availability</Secondary_Categories><SSL_Support>Yes</SSL_Support><Primary_Category>Travel</Primary_Category></API>