<?xml version="1.0" encoding="utf-8" standalone="no"?><API><API_Name>Gradwell Call</API_Name><Contact_Email>info@gradwell.com</Contact_Email><API_Homepage>https://support.gradwell.com/entries/23136221-How-use-the-call-API-functionality</API_Homepage><API_Endpoint>https://call-api.gradwell.com/0.9.3/call</API_Endpoint><API_Provider>http://www.gradwell.com/</API_Provider><APIhub_URL/><Protocol___Formats>REST </Protocol___Formats><Secondary_Categories>Enterprise</Secondary_Categories><Primary_Category>Telephony</Primary_Category></API>