<?xml version="1.0" encoding="utf-8" standalone="no"?><API><API_Name>Hawkesbury City Council Masterview</API_Name><Contact_Email>council@hawkesbury.nsw.gov.au</Contact_Email><API_Homepage>http://council.hawkesbury.nsw.gov.au/MasterViewUI/Modules/Applicationmaster/Defa...</API_Homepage><API_Provider>http://www.hawkesbury.nsw.gov.au/</API_Provider><APIhub_URL/><Protocol___Formats>SOAP </Protocol___Formats><Secondary_Categories>Australian</Secondary_Categories><Primary_Category>Government</Primary_Category></API>