<?xml version="1.0" encoding="utf-8" standalone="no"?><API><API_Name>Intel CPU</API_Name><API_Homepage>http://software.intel.com/en-us/articles/intel-cpu-web-api-documentation-and-exa...</API_Homepage><API_Provider>http://www.intel.com</API_Provider><APIhub_URL/><Protocol___Formats>JSON </Protocol___Formats><Developer_Support>http://software.intel.com/en-us/forums/intel-web-apis/</Developer_Support><API_Forum>http://software.intel.com/en-us/forums/intel-web-apis/</API_Forum><Other_options>JavaScript</Other_options></API>