<?xml version="1.0" encoding="utf-8" standalone="no"?><API><API_Name>LDSTech Gospel Library Catalog</API_Name><Contact_Email>tech@ldschurch.org</Contact_Email><API_Homepage>http://tech.lds.org/wiki/Gospel_Library_Catalog_Web_Service</API_Homepage><API_Endpoint>http://tech.lds.org/glweb</API_Endpoint><API_Provider>http://www.lds.org/</API_Provider><APIhub_URL/><Protocol___Formats>REST </Protocol___Formats><Secondary_Categories>Religion</Secondary_Categories><Primary_Category>Search</Primary_Category></API>