<?xml version="1.0" encoding="utf-8" standalone="no"?><API><API_Name>LiqPAY</API_Name><API_Homepage>https://liqpay.com/?do=pages&amp;amp;p=apiwelcome</API_Homepage><Twitter_Url>http://twitter.com/liqpay</Twitter_Url><API_Kits>PHP, Perl</API_Kits><API_Endpoint>https://liqpay.com?/do=api_xml</API_Endpoint><API_Provider>http://www.liqpay.com</API_Provider><APIhub_URL/><Protocol___Formats>XML </Protocol___Formats><Authentication_Mode>Basic authentication over SSL</Authentication_Mode><SSL_Support>Yes</SSL_Support><Primary_Category>Payments</Primary_Category></API>