<?xml version="1.0" encoding="utf-8" standalone="no"?><API><API_Name>Mailup</API_Name><Contact_Email>sales@mailup.com</Contact_Email><API_Homepage>http://www.mailup.com/mailup-api-web-services-integrations.htm</API_Homepage><API_Kits>C#</API_Kits><API_Endpoint>http://services.mailupnet.it/</API_Endpoint><API_Provider>http://www.mailup.com/p/pc/Homepage-d40.htm</API_Provider><APIhub_URL/><Protocol___Formats>SOAP </Protocol___Formats><Developer_Support>http://www.mailup.com/support/IntegrationProcedures.pdf</Developer_Support><Authentication_Mode>HTTP Basic Authentication IP-specific</Authentication_Mode><Secondary_Categories>Marketing</Secondary_Categories><SSL_Support>No</SSL_Support><Primary_Category>Email</Primary_Category></API>