<?xml version="1.0" encoding="utf-8" standalone="no"?><API><API_Name>MessageMedia SMS</API_Name><Contact_Email>salesteam@message-media.com</Contact_Email><API_Homepage>http://www.message-media.com/business/developers</API_Homepage><API_Kits>.NET, PHP, Java, COM</API_Kits><API_Provider>http://www.message-media.com</API_Provider><APIhub_URL/><Developer_Support>http://www.message-media.com/support.html</Developer_Support><Authentication_Mode>HTTPS</Authentication_Mode><Other_options>SMS</Other_options><Secondary_Categories>Telephony</Secondary_Categories><SSL_Support>Yes</SSL_Support><Primary_Category>Messaging</Primary_Category></API>