<?xml version="1.0" encoding="utf-8" standalone="no"?><API><API_Name>Minube</API_Name><Contact_Email>equipotecnico@minube.com</Contact_Email><API_Homepage>http://www.minube.com/api</API_Homepage><API_Endpoint>http://api.minube.com/locations/countries.{format}</API_Endpoint><API_Provider>http://www.minube.com</API_Provider><APIhub_URL/><Protocol___Formats>REST </Protocol___Formats><Authentication_Mode>API Key</Authentication_Mode><Secondary_Categories>Social</Secondary_Categories><SSL_Support>No</SSL_Support><Primary_Category>Travel</Primary_Category></API>