<?xml version="1.0" encoding="utf-8" standalone="no"?><API><API_Name>Moodstocks</API_Name><API_Homepage>https://github.com/Moodstocks/moodstocks-api/wiki/api-v2-doc</API_Homepage><API_Kits>ObjectiveC, Java (Android) C#</API_Kits><API_Provider>http://www.moodstocks.com</API_Provider><Protocol___Formats>REST </Protocol___Formats><SSL_Support>No</SSL_Support><Contact_Email>contact@moodstocks.com</Contact_Email><API_Endpoint>http://api.moodstocks.com/v2/</API_Endpoint><Twitter_Url>http://twitter.com/moodstocks</Twitter_Url><APIhub_URL/><Developer_Support>http://help.moodstocks.com/</Developer_Support><Authentication_Mode>API Key, HTTP Digest</Authentication_Mode><Secondary_Categories>Mobile</Secondary_Categories><Primary_Category>Photos</Primary_Category></API>