<?xml version="1.0" encoding="utf-8" standalone="no"?><API><API_Name>Morale</API_Name><Contact_Email>github@brilliantfantastic.com</Contact_Email><API_Homepage>https://www.teammorale.com/docs/api</API_Homepage><API_Endpoint>http://&amp;lt;subdomain&amp;gt;.teammorale.com/api/</API_Endpoint><API_Provider>http://brilliantfantastic.com/</API_Provider><APIhub_URL/><Protocol___Formats>REST </Protocol___Formats><Developer_Support>http://teammorale.com/docs/api</Developer_Support><API_Forum>http://support.teammorale.com/home</API_Forum><Authentication_Mode>Basic Authentication with API Key</Authentication_Mode><Secondary_Categories>Social</Secondary_Categories><SSL_Support>Yes</SSL_Support><Primary_Category>Project Management</Primary_Category></API>