<?xml version="1.0" encoding="utf-8" standalone="no"?><API><API_Name>Music Xray S2O Partner</API_Name><Contact_Email>business@musicxray.com</Contact_Email><API_Homepage>http://docs.musicxray.com/</API_Homepage><API_Kits>Ruby</API_Kits><API_Endpoint>https://api.musicxray.com/</API_Endpoint><API_Provider>http://www.musicxray.com/</API_Provider><APIhub_URL/><Protocol___Formats>REST </Protocol___Formats><Developer_Support>http://docs.musicxray.com/</Developer_Support><Authentication_Mode>API Key</Authentication_Mode><Secondary_Categories>Social</Secondary_Categories><SSL_Support>Yes</SSL_Support><Primary_Category>Music</Primary_Category></API>