<?xml version="1.0" encoding="utf-8" standalone="no"?><API><API_Name>Netatmo</API_Name><API_Homepage>http://dev.netatmo.com/doc/</API_Homepage><API_Kits>PHP, Objective-C, Windows 8, Java</API_Kits><API_Endpoint>http://api.netatmo.net/api/</API_Endpoint><API_Provider>www.netatmo.com/en-US/site</API_Provider><APIhub_URL/><Protocol___Formats>REST </Protocol___Formats><Authentication_Mode>OAuth 2</Authentication_Mode><Secondary_Categories>Mobile</Secondary_Categories><Primary_Category>Weather</Primary_Category></API>