<?xml version="1.0" encoding="utf-8" standalone="no"?><API><API_Name>New York Times Districts</API_Name><Contact_Email>code@nytimes.com</Contact_Email><API_Homepage>http://developer.nytimes.com/docs/districts_api</API_Homepage><API_Endpoint>http://api.nytimes.com/svc/politics/v2/</API_Endpoint><API_Provider>http://nytimes.com</API_Provider><APIhub_URL/><Protocol___Formats>REST </Protocol___Formats><API_Forum>http://developer.nytimes.com/forum</API_Forum><Authentication_Mode>API Key</Authentication_Mode><Secondary_Categories>Reference</Secondary_Categories><Primary_Category>Government</Primary_Category></API>