<?xml version="1.0" encoding="utf-8" standalone="no"?><API><API_Name>Oneall</API_Name><Contact_Email>cschlesser@oneall.com</Contact_Email><API_Homepage>http://docs.oneall.com/</API_Homepage><API_Provider>http://www.oneall.com</API_Provider><APIhub_URL/><Protocol___Formats>REST </Protocol___Formats><Developer_Support>http://docs.oneall.com/api/</Developer_Support><Authentication_Mode>HTTP Basic Auth over SSL, API Key</Authentication_Mode><Secondary_Categories>Authentication</Secondary_Categories><SSL_Support>Yes</SSL_Support><Primary_Category>Social</Primary_Category></API>