<?xml version="1.0" encoding="utf-8" standalone="no"?><API><API_Name>OP3Nvoice</API_Name><Contact_Email>support@op3nvoice.com</Contact_Email><API_Homepage>https://dev-beta.op3nvoice.com/</API_Homepage><Twitter_Url>OP3Nvoice</Twitter_Url><API_Endpoint>https://api-beta.op3nvoice.com/</API_Endpoint><API_Provider>http://www.op3nvoice.com/</API_Provider><APIhub_URL/><Protocol___Formats>REST </Protocol___Formats><Developer_Support>support@op3nvoice.com</Developer_Support><Authentication_Mode>API Key, Token</Authentication_Mode><Secondary_Categories>Video</Secondary_Categories><SSL_Support>Yes</SSL_Support><Primary_Category>Media</Primary_Category></API>