<?xml version="1.0" encoding="utf-8" standalone="no"?><API><API_Name>OpenSnow</API_Name><Contact_Email>hello@opensnow.com</Contact_Email><API_Homepage>http://opensnow.com/about/api</API_Homepage><API_Endpoint>http://opensnow.com/api/</API_Endpoint><API_Provider>http://opensnow.com/</API_Provider><APIhub_URL/><Protocol___Formats>REST </Protocol___Formats><Authentication_Mode>API Key</Authentication_Mode><Secondary_Categories>Sports</Secondary_Categories><Primary_Category>Weather</Primary_Category></API>