<?xml version="1.0" encoding="utf-8" standalone="no"?><API><API_Name>openfooty</API_Name><API_Homepage>http://www.footytube.com/openfooty/</API_Homepage><API_Endpoint>http://v1.openfooty.org/</API_Endpoint><API_Provider>http://www.footytube.com</API_Provider><APIhub_URL/><Protocol___Formats>REST </Protocol___Formats><Developer_Support>http://www.footytube.com/forums/developer-forum/</Developer_Support><Authentication_Mode>API Key</Authentication_Mode><Other_options>Serialized PHP</Other_options><SSL_Support>No</SSL_Support><Primary_Category>Sports</Primary_Category></API>