<?xml version="1.0" encoding="utf-8" standalone="no"?><API><API_Name>openDada</API_Name><API_Homepage>http://access.motime.com/tools/cat_28</API_Homepage><API_Kits>PHP, Perl, and Ruby sample code</API_Kits><API_Endpoint>http://api.dada-ent.com</API_Endpoint><API_Provider>http://opendada.com</API_Provider><APIhub_URL/><Protocol___Formats>REST </Protocol___Formats><API_Forum>http://opendada.com/forum</API_Forum><Authentication_Mode>API Key</Authentication_Mode><Secondary_Categories>Social</Secondary_Categories><SSL_Support>No</SSL_Support><Primary_Category>Music</Primary_Category></API>