<?xml version="1.0" encoding="utf-8" standalone="no"?><API><API_Name>Pactas</API_Name><Contact_Email>support@pactas.com</Contact_Email><API_Homepage>http://developer.pactas.com/Docs/Reference</API_Homepage><API_Endpoint>https://itero.pactas.com/</API_Endpoint><API_Provider>http://www.pactas.com</API_Provider><APIhub_URL/><Protocol___Formats>REST </Protocol___Formats><Authentication_Mode>HTTP Basic Authentication, OAuth</Authentication_Mode><Secondary_Categories>Contracts</Secondary_Categories><SSL_Support>Yes</SSL_Support><Primary_Category>Financial</Primary_Category></API>