<?xml version="1.0" encoding="utf-8" standalone="no"?><API><API_Name>paysafecard</API_Name><Contact_Email>techsupport@paysafecard.com</Contact_Email><API_Homepage>https://www.paysafecard.com/en-global/business/downloads/</API_Homepage><Twitter_Url>https://twitter.com/paysafecard</Twitter_Url><API_Provider>http://www.paysafecard.com/</API_Provider><APIhub_URL/><Protocol___Formats>SOAP </Protocol___Formats><Developer_Support>http://www.paysafecard.com/fileadmin/content/Technischer_Download/SOAP/20121029_SOPG_ClassicMerchant_2.3__EN_.pdf</Developer_Support><Authentication_Mode>HTTP Basic Authentication</Authentication_Mode><Secondary_Categories>England</Secondary_Categories><SSL_Support>Yes</SSL_Support><Primary_Category>Payments</Primary_Category></API>