<?xml version="1.0" encoding="utf-8" standalone="no"?><API><API_Name>Plancast</API_Name><Contact_Email>support@plancast.com</Contact_Email><API_Homepage>http://plancast.com/api</API_Homepage><API_Kits>Ruby, Python</API_Kits><API_Endpoint>http://api.plancast.com</API_Endpoint><API_Provider>http://plancast.com</API_Provider><APIhub_URL/><Protocol___Formats>REST </Protocol___Formats><Developer_Support>http://getsatisfaction.com/plancast</Developer_Support><Authentication_Mode>HTTP Basic Authentication</Authentication_Mode><Secondary_Categories>Events</Secondary_Categories><SSL_Support>No</SSL_Support><Primary_Category>Social</Primary_Category></API>