<?xml version="1.0" encoding="utf-8" standalone="no"?><API><API_Name>RoboWhois</API_Name><Contact_Email>support@robodomain.com</Contact_Email><API_Homepage>https://www.robowhois.com/</API_Homepage><API_Endpoint>http://api.robowhois.com/</API_Endpoint><API_Provider>http://www.robowhois.com/</API_Provider><APIhub_URL/><Protocol___Formats>JSON </Protocol___Formats><Authentication_Mode>HTTP Basic Authentication</Authentication_Mode><Other_options>HTTP POST</Other_options><Secondary_Categories>Domains</Secondary_Categories><Primary_Category>Domains</Primary_Category></API>