<?xml version="1.0" encoding="utf-8" standalone="no"?><API><API_Name>Scalr</API_Name><API_Homepage>https://scalr-wiki.atlassian.net/wiki/display/docs/Home</API_Homepage><API_Endpoint>https://api.scalr.net/</API_Endpoint><API_Provider>http://scalr.net</API_Provider><APIhub_URL/><Protocol___Formats>XML </Protocol___Formats><Authentication_Mode>API Key</Authentication_Mode><Other_options>REST-RPC</Other_options><Secondary_Categories>Webhooks</Secondary_Categories><Primary_Category>Hosting</Primary_Category></API>