<?xml version="1.0" encoding="utf-8" standalone="no"?><API><API_Name>Simunix T2A</API_Name><API_Homepage>http://t2a.co/services/find_people/find_people_at_address</API_Homepage><API_Kits>Java</API_Kits><API_Provider>http://www.simunix.com</API_Provider><Protocol___Formats>SOAP </Protocol___Formats><SSL_Support>Yes</SSL_Support><Contact_Email>info@simunix.com</Contact_Email><API_Endpoint>http://t2a.co/rest/</API_Endpoint><Twitter_Url>http://twitter.com/t2adotco</Twitter_Url><APIhub_URL/><Developer_Support>http://t2a.co/phpBB3/index.php</Developer_Support><API_Forum>http://t2a.co/phpBB3/index.php</API_Forum><Authentication_Mode>API Key</Authentication_Mode><Secondary_Categories>Telephony</Secondary_Categories><Primary_Category>Reference</Primary_Category></API>