<?xml version="1.0" encoding="utf-8" standalone="no"?><API><API_Name>Spizter Heritage Archive</API_Name><API_Homepage>http://irsa.ipac.caltech.edu/onlinehelp/heritage/api.html</API_Homepage><API_Endpoint>http://sha.ipac.caltech.edu/applications/Spitzer/SHA/servlet/DataService?</API_Endpoint><API_Provider>http://irsa.ipac.caltech.edu</API_Provider><APIhub_URL/><Protocol___Formats>HTTP </Protocol___Formats><Secondary_Categories>Astronomy</Secondary_Categories><Primary_Category>Science</Primary_Category></API>