<?xml version="1.0" encoding="utf-8" standalone="no"?><API><API_Name>Spreadshirt</API_Name><Contact_Email>http://www.spreadshirt.net/en/IE/About-us/Contact-1336/</Contact_Email><API_Homepage>http://spreadshop.org/</API_Homepage><API_Provider>http://www.spreadshirt.net</API_Provider><APIhub_URL/><Protocol___Formats>SOAP </Protocol___Formats><Developer_Support>http://developer.spreadshirt.net/display/API/Home</Developer_Support><API_Forum>http://forum.spreadshirt.net/forumdisplay.php?f=47</API_Forum><Secondary_Categories>Clothing</Secondary_Categories><Primary_Category>eCommerce</Primary_Category></API>