<?xml version="1.0" encoding="utf-8" standalone="no"?><API><API_Name>Versatility Werks</API_Name><Contact_Email>hey@verswerks.com </Contact_Email><API_Homepage>Anti-Spam Captcha and BOT IP blocker</API_Homepage><Twitter_Url>https://twitter.com/verswerks</Twitter_Url><API_Endpoint>https://verswerks-anti-spam-captcha-and-bot-ip-blocker.p.mashape.com/generate-captch</API_Endpoint><API_Provider>http://flwebsites.biz/</API_Provider><APIhub_URL/><Protocol___Formats>REST </Protocol___Formats><Developer_Support>http://flwebsites.biz/contact</Developer_Support><Authentication_Mode>API Key</Authentication_Mode><Secondary_Categories>Spam</Secondary_Categories><SSL_Support>Yes</SSL_Support><Primary_Category>Captcha</Primary_Category></API>