<?xml version="1.0" encoding="utf-8" standalone="no"?><API><API_Name>ViaNett</API_Name><Contact_Email>smssupport@vianett.com</Contact_Email><API_Homepage>http://www.vianett.com/en/developers/sms-api-overview</API_Homepage><API_Kits>ASP, .NET, C#, Java, MSSQL, PHP, VB</API_Kits><API_Endpoint>http://smsc.vianett.no/ActiveServer/</API_Endpoint><API_Provider>http://sms.vianett.com</API_Provider><APIhub_URL/><Protocol___Formats>SMTP </Protocol___Formats><Authentication_Mode>User Password</Authentication_Mode><SSL_Support>Yes</SSL_Support><Primary_Category>Messaging</Primary_Category></API>