<?xml version="1.0" encoding="utf-8" standalone="no"?><API><API_Name>Walk Score Travel Time</API_Name><API_Homepage>http://www.walkscore.com/professional/travel-time-api.php</API_Homepage><API_Endpoint>http://apicdn.walkscore.com/api/v1/traveltime</API_Endpoint><API_Provider>http://www.walkscore.com/</API_Provider><APIhub_URL/><Protocol___Formats>REST </Protocol___Formats><Authentication_Mode>API Key</Authentication_Mode><Secondary_Categories>Fitness</Secondary_Categories><SSL_Support>No</SSL_Support><Primary_Category>Transportation</Primary_Category></API>