<?xml version="1.0" encoding="utf-8" standalone="no"?><API><API_Name>WebGL Earth</API_Name><Contact_Email>info@klokantech.com</Contact_Email><API_Homepage>http://www.webglearth.org/api</API_Homepage><API_Endpoint>http://www.webglearth.com/api.js</API_Endpoint><API_Provider>http://www.klokantech.com/</API_Provider><APIhub_URL/><API_Forum>http://webglearth.uservoice.com/forums/93887-general</API_Forum><Other_options>JavaScript</Other_options><Secondary_Categories>3D</Secondary_Categories><Primary_Category>Mapping</Primary_Category></API>