<CategoryNode>
	<Name>Base Web Service</Name>
	<Weight>1.0</Weight>
	<Childs>
	<CategoryNode>
		<Name>Static Attribute</Name>
		<Weight>0.5303119807209836</Weight>
		<Childs>
		<CategoryNode>
			<Name>Security</Name>
			<Weight>0.27033355028399536</Weight>
			<Childs>
			<FactorNode>
				<Name>Encryption algorithm</Name>
				<Weight>0.04412734385379464</Weight>
			</FactorNode>
			<FactorNode>
				<Name>Traceability rating</Name>
				<Weight>0.04458618901556272</Weight>
			</FactorNode>
			<FactorNode>
				<Name>Classified level</Name>
				<Weight>0.03933864876859998</Weight>
			</FactorNode>
			<FactorNode>
				<Name>Access</Name>
				<Weight>0.14228136864603802</Weight>
			</FactorNode>
			</Childs>
		</CategoryNode>
		<FactorNode>
			<Name>fee</Name>
			<Weight>0.038430016640303225</Weight>
		</FactorNode>
		<CategoryNode>
			<Name>Robustness</Name>
			<Weight>0.08296561573560995</Weight>
			<Childs>
			<FactorNode>
				<Name>Exception handling capability</Name>
				<Weight>0.04210065567604119</Weight>
			</FactorNode>
			<FactorNode>
				<Name>Self-recovery capability</Name>
				<Weight>0.040864960059568765</Weight>
			</FactorNode>
			</Childs>
		</CategoryNode>
		<FactorNode>
			<Name>Interface stability</Name>
			<Weight>0.1385827980610751</Weight>
		</FactorNode>
		</Childs>
	</CategoryNode>
	<CategoryNode>
		<Name>Dynamic Attribute</Name>
		<Weight>0.4696880192790163</Weight>
		<Childs>
		<CategoryNode>
			<Name>Performance</Name>
			<Weight>0.07269764252975204</Weight>
			<Childs>
			<FactorNode>
				<Name>Throughput</Name>
				<Weight>0.02514316489581408</Weight>
			</FactorNode>
			<FactorNode>
				<Name>Delay</Name>
				<Weight>0.024933991395472335</Weight>
			</FactorNode>
			<FactorNode>
				<Name>Service run time</Name>
				<Weight>0.022620486238465628</Weight>
			</FactorNode>
			</Childs>
		</CategoryNode>
		<CategoryNode>
			<Name>Availability</Name>
			<Weight>0.11458436534646403</Weight>
			<Childs>
			<FactorNode>
				<Name>Response time</Name>
				<Weight>0.11458436534646403</Weight>
			</FactorNode>
			</Childs>
		</CategoryNode>
		<CategoryNode>
			<Name>Reputation</Name>
			<Weight>0.042714864496089425</Weight>
			<Childs>
			<FactorNode>
				<Name>User satisfaction</Name>
				<Weight>0.042714864496089425</Weight>
			</FactorNode>
			</Childs>
		</CategoryNode>
		<CategoryNode>
			<Name>Reliability</Name>
			<Weight>0.23969114690671084</Weight>
			<Childs>
			<FactorNode>
				<Name>Average Response Time</Name>
				<Weight>0.05471729293197067</Weight>
			</FactorNode>
			<FactorNode>
				<Name>Call Success Rate</Name>
				<Weight>0.03311117621899934</Weight>
			</FactorNode>
			<FactorNode>
				<Name>Consistency</Name>
				<Weight>0.15186267775574083</Weight>
			</FactorNode>
			</Childs>
		</CategoryNode>
		</Childs>
	</CategoryNode>
	</Childs>
</CategoryNode>
